Workbook

Sheet 1. Portfolio Detail
A1: Sr. no. | B1: EAD | C1: PD | D1: LGD | E1: Interest Rate
A2: 1 | B2: 2.1113429 | C2: 0.056981572 | D2: 0.35169593 | E2: 0.11575387
A3: 2 | B3: 5.2990655 | C3: 0.048475992 | D3: 0.3390387 | E3: 0.11992567
A4: 3 | B4: 7.6585824 | C4: 0.020339055 | D4: 0.69064928 | E4: 0.12589962
A5: 4 | B5: 10.038626 | C5: 0.039190503 | D5: 0.24844378 | E5: 0.12382281
A6: 5 | B6: 3.3824982 | C6: 0.049807074 | D6: 0.4769278 | E6: 0.10149116
A7: 6 | B7: 3.4972014 | C7: 0.011442721 | D7: 0.36116161 | E7: 0.1313683
A8: 7 | B8: 5.8462904 | C8: 0.015967169 | D8: 0.26492404 | E8: 0.1114443
A9: 8 | B9: 7.9710898 | C9: 0.043499081 | D9: 0.24926485 | E9: 0.10761221
A10: 9 | B10: 8.1065641 | C10: 0.010114371 | D10: 0.21409737 | E10: 0.13082757
A11: 10 | B11: 6.7961997 | C11: 0.039033389 | D11: 0.31568127 | E11: 0.12959775
A12: 11 | B12: 8.3969893 | C12: 0.027673694 | D12: 0.44498065 | E12: 0.10631617
A13: 12 | B13: 8.5308127 | C13: 0.049376226 | D13: 0.32100409 | E13: 0.13530221
... A101: 100 | B101: 4.1876167 | C101: 0.045849843 | D101: 0.62765712 | E101: 0.12479544

Sheet 2. Working sheet
A1: Summary | L1: Formulas
B2: Total Value | C2: Mean (µ) | D2: Std Dev (σ) | L2: Expected Loss (EL) = EAD x PD x LGD
A3: EAD | B3: =+'2. Working sheet'!$B$8 -> 584.374 | C3: =+AVERAGE('2. Working sheet'!B10:B109) -> 5.84374 | D3: =+_xlfn.STDEV.P('2. Working sheet'!B10:B109) -> 2.9575157 | L3: Unexpected Loss (UL) = EAD*(SQRT((PD*Variance LGD)+((LGD^2)*Variance PD)))
A4: PD | B4: - | C4: =+AVERAGE('2. Working sheet'!C10:C109) -> 0.035706631 | D4: =+_xlfn.STDEV.P('2. Working sheet'!C10:C109) -> 0.015427861 | L4: Interest Income = EAD x Interest %
A5: LGD | B5: - | C5: =+AVERAGE('2. Working sheet'!D10:D109) -> 0.44719691 | D5: =+_xlfn.STDEV.P('2. Working sheet'!D10:D109) -> 0.15144769
A8: Total | B8: =SUM(B10:B109) -> 584.374 | E8: =SUM(E10:E109) -> 9.0075568 | H8: =SUM(H10:H109) -> 49.369273 | J8: =SUM(J10:J109) -> 68.833739
A9: Sl No: | B9: EAD ($mn) | C9: PD | D9: LGD | E9: EL | F9: Variance PD | G9: Variance LGD | H9: UL | I9: Int % | J9: Int Inc($mn)
A10: 1 | B10: =+'1. Portfolio Detail'!B2 -> 2.1113429 | C10: =+'1. Portfolio Detail'!C2 -> 0.056981572 | D10: =+'1. Portfolio Detail'!D2 -> 0.35169593 | E10: =+B10*C10*D10 -> 0.042311707 | F10: =+C10*(1-C10) -> 0.053734672 | G10: =+(D10-'2. Working sheet'!$C$5)^2 -> 0.0091204379 | H10: =+B10*(SQRT((C10*G10)+((D10^2)*F10))) -> 0.17873163 | I10: =+'1. Portfolio Detail'!E2 -> 0.11575387 | J10: =+I10*B10 -> 0.24439612
A11: 2 | B11: =+'1. Portfolio Detail'!B3 -> 5.2990655 | C11: =+'1. Portfolio Detail'!C3 -> 0.048475992 | D11: =+'1. Portfolio Detail'!D3 -> 0.3390387 | E11: =+B11*C11*D11 -> 0.0870914 | F11: =+C11*(1-C11) -> 0.04612607 | G11: =+(D11-'2. Working sheet'!$C$5)^2 -> 0.011698198 | H11: =+B11*(SQRT((C11*G11)+((D11^2)*F11))) -> 0.40596328 | I11: =+'1. Portfolio Detail'!E3 -> 0.11992567 | J11: =+I11*B11 -> 0.63549398
A12: 3 | B12: =+'1. Portfolio Detail'!B4 -> 7.6585824 | C12: =+'1. Portfolio Detail'!C4 -> 0.020339055 | D12: =+'1. Portfolio Detail'!D4 -> 0.69064928 | E12: =+B12*C12*D12 -> 0.10758128 | F12: =+C12*(1-C12) -> 0.019925378 | G12: =+(D12-'2. Working sheet'!$C$5)^2 -> 0.059269055 | H12: =+B12*(SQRT((C12*G12)+((D12^2)*F12))) -> 0.79257302 | I12: =+'1. Portfolio Detail'!E4 -> 0.12589962 | J12: =+I12*B12 -> 0.96421259
A13: 4 | B13: =+'1. Portfolio Detail'!B5 -> 10.038626 | C13: =+'1. Portfolio Detail'!C5 -> 0.039190503 | D13: =+'1. Portfolio Detail'!D5 -> 0.24844378 | E13: =+B13*C13*D13 -> 0.097742456 | F13: =+C13*(1-C13) -> 0.037654608 | G13: =+(D13-'2. Working sheet'!$C$5)^2 -> 0.039502805 | H13: =+B13*(SQRT((C13*G13)+((D13^2)*F13))) -> 0.62468488 | I13: =+'1. Portfolio Detail'!E5 -> 0.12382281 | J13: =+I13*B13 -> 1.2430109
A14: 5 | B14: =+'1. Portfolio Detail'!B6 -> 3.3824982 | C14: =+'1. Portfolio Detail'!C6 -> 0.049807074 | D14: =+'1. Portfolio Detail'!D6 -> 0.4769278 | E14: =+B14*C14*D14 -> 0.080349142 | F14: =+C14*(1-C14) -> 0.047326329 | G14: =+(D14-'2. Working sheet'!$C$5)^2 -> 0.00088392577 | H14: =+B14*(SQRT((C14*G14)+((D14^2)*F14))) -> 0.35166399 | I14: =+'1. Portfolio Detail'!E6 -> 0.10149116 | J14: =+I14*B14 -> 0.34329367
A15: 6 | B15: =+'1. Portfolio Detail'!B7 -> 3.4972014 | C15: =+'1. Portfolio Detail'!C7 -> 0.011442721 | D15: =+'1. Portfolio Detail'!D7 -> 0.36116161 | E15: =+B15*C15*D15 -> 0.014452784 | F15: =+C15*(1-C15) -> 0.011311785 | G15: =+(D15-'2. Working sheet'!$C$5)^2 -> 0.0074020723 | H15: =+B15*(SQRT((C15*G15)+((D15^2)*F15))) -> 0.1381365 | I15: =+'1. Portfolio Detail'!E7 -> 0.1313683 | J15: =+I15*B15 -> 0.45942139
A16: 7 | B16: =+'1. Portfolio Detail'!B8 -> 5.8462904 | C16: =+'1. Portfolio Detail'!C8 -> 0.015967169 | D16: =+'1. Portfolio Detail'!D8 -> 0.26492404 | E16: =+B16*C16*D16 -> 0.024730317 | F16: =+C16*(1-C16) -> 0.015712219 | G16: =+(D16-'2. Working sheet'!$C$5)^2 -> 0.0332234 | H16: =+B16*(SQRT((C16*G16)+((D16^2)*F16))) -> 0.23626839 | I16: =+'1. Portfolio Detail'!E8 -> 0.1114443 | J16: =+I16*B16 -> 0.65153575
A17: 8 | B17: =+'1. Portfolio Detail'!B9 -> 7.9710898 | C17: =+'1. Portfolio Detail'!C9 -> 0.043499081 | D17: =+'1. Portfolio Detail'!D9 -> 0.24926485 | E17: =+B17*C17*D17 -> 0.086428867 | F17: =+C17*(1-C17) -> 0.041606911 | G17: =+(D17-'2. Working sheet'!$C$5)^2 -> 0.039177101 | H17: =+B17*(SQRT((C17*G17)+((D17^2)*F17))) -> 0.52205032 | I17: =+'1. Portfolio Detail'!E9 -> 0.10761221 | J17: =+I17*B17 -> 0.85778663
A18: 9 | B18: =+'1. Portfolio Detail'!B10 -> 8.1065641 | C18: =+'1. Portfolio Detail'!C10 -> 0.010114371 | D18: =+'1. Portfolio Detail'!D10 -> 0.21409737 | E18: =+B18*C18*D18 -> 0.017554443 | F18: =+C18*(1-C18) -> 0.010012071 | G18: =+(D18-'2. Working sheet'!$C$5)^2 -> 0.054335393 | H18: =+B18*(SQRT((C18*G18)+((D18^2)*F18))) -> 0.25743906 | I18: =+'1. Portfolio Detail'!E10 -> 0.13082757 | J18: =+I18*B18 -> 1.0605621
A19: 10 | B19: =+'1. Portfolio Detail'!B11 -> 6.7961997 | C19: =+'1. Portfolio Detail'!C11 -> 0.039033389 | D19: =+'1. Portfolio Detail'!D11 -> 0.31568127 | E19: =+B19*C19*D19 -> 0.08374352 | F19: =+C19*(1-C19) -> 0.037509784 | G19: =+(D19-'2. Working sheet'!$C$5)^2 -> 0.017296363 | H19: =+B19*(SQRT((C19*G19)+((D19^2)*F19))) -> 0.45148258 | I19: =+'1. Portfolio Detail'!E11 -> 0.12959775 | J19: =+I19*B19 -> 0.88077217
A20: 11 | B20: =+'1. Portfolio Detail'!B12 -> 8.3969893 | C20: =+'1. Portfolio Detail'!C12 -> 0.027673694 | D20: =+'1. Portfolio Detail'!D12 -> 0.44498065 | E20: =+B20*C20*D20 -> 0.1034027 | F20: =+C20*(1-C20) -> 0.026907861 | G20: =+(D20-'2. Working sheet'!$C$5)^2 -> 4.9118009e-06 | H20: =+B20*(SQRT((C20*G20)+((D20^2)*F20))) -> 0.61292855 | I20: =+'1. Portfolio Detail'!E12 -> 0.10631617 | J20: =+I20*B20 -> 0.89273573
A21: 12 | B21: =+'1. Portfolio Detail'!B13 -> 8.5308127 | C21: =+'1. Portfolio Detail'!C13 -> 0.049376226 | D21: =+'1. Portfolio Detail'!D13 -> 0.32100409 | E21: =+B21*C21*D21 -> 0.13521313 | F21: =+C21*(1-C21) -> 0.046938215 | G21: =+(D21-'2. Working sheet'!$C$5)^2 -> 0.015924628 | H21: =+B21*(SQRT((C21*G21)+((D21^2)*F21))) -> 0.63969616 | I21: =+'1. Portfolio Detail'!E13 -> 0.13530221 | J21: =+I21*B21 -> 1.1542379
... A109: 100 | B109: =+'1. Portfolio Detail'!B101 -> 4.1876167 | C109: =+'1. Portfolio Detail'!C101 -> 0.045849843 | D109: =+'1. Portfolio Detail'!D101 -> 0.62765712 | E109: =+B109*C109*D109 -> 0.12051115 | F109: =+C109*(1-C109) -> 0.043747635 | G109: =+(D109-'2. Working sheet'!$C$5)^2 -> 0.032565888 | H109: =+B109*(SQRT((C109*G109)+((D109^2)*F109))) -> 0.57307153 | I109: =+'1. Portfolio Detail'!E101 -> 0.12479544 | J109: =+I109*B109 -> 0.52259547

Sheet 3. Decision Maker
A1: Hurdle Rate Computation
B2: Amount ($mn) | C2: Cost of Capital (%) | D2: Cost of Capital ($mn)
A3: Equity Capital | B3: 3000 | C3: 0.1 | D3: =+C3*B3 -> 300
A4: Preferencial Capital | B4: 2000 | C4: 0.09 | D4: =+C4*B4 -> 180
B5: =SUM(B3:B4) -> 5000 | D5: =SUM(D3:D4) -> 480
D6: =+D5/B5 -> 0.096
A7: Economic Capital Computation
A8: VAR (set at bank level) | B8: 0.9997
A9: Capital Multiplier | B9: =+_xlfn.NORM.S.INV(B8) -> 3.4316144
A10: Economic Capital (ULp*CM) | B10: =+'2. Working sheet'!H8*B9 -> 169.41631
A13: RAROC Computation
A14: Porfolio Income | B14: =+'2. Working sheet'!J8 -> 68.833739
A15: Less: Cost of Loan Funding @9% | B15: =+'2. Working sheet'!$B$8*0.09 -> 52.59366
A16: Less: Expected Loss | B16: =+'2. Working sheet'!$E$8 -> 9.0075568
A17: Risk Adjusted Return before tax | B17: =+B14-B15-B16 -> 7.2325218
A18: Less: Tax @ 30% | B18: =+B17*0.3 -> 2.1697566
A19: Risk Adjusted Return after tax | B19: =+B17-B18 -> 5.0627653
A20: Economic Capital | B20: ='3. Decision Maker'!B10 -> 169.41631
A21: RAROC | B21: =+B19/B20 -> 0.029883577
A24: Decision Maker
A25: RAROC-Hurdle Rate | B25: =+B21-D6 -> -0.066116423
A26: RAROC > Hurdle Rate? | B26: =+IF(B21>D6,"Yes","No") -> No
A27: Project to be approved? | B27: =+IF(B26="Yes","Yes","No") -> No
